shareable/__init__.py
shareable/managers_decorators.py
shareable/producers.py
shareable/shareable.py
shareable/shared_objects.py
tests/__init__.py
tests/shareable_test.py
tests/single_state.py
tests/test_class.py
shareable-0.6a0.dist-info/LICENSE
shareable-0.6a0.dist-info/METADATA
shareable-0.6a0.dist-info/WHEEL
shareable-0.6a0.dist-info/top_level.txt
shareable-0.6a0.dist-info/RECORD
