Metadata-Version: 2.1
Name: shareable
Version: 0.6a0
Summary: Dynamic python object access & manipulation across threads/processes.
Home-page: https://github.com/greysonlalonde/shareable
Author: Greyson R. LaLonde
Author-email: greyson.r.lalonde@gmail.com
License: MIT
Download-URL: https://github.com/greysonlalonde/shareable/v0.6-alpha.tar.gz
Platform: UNKNOWN
Classifier: License :: OSI Approved :: MIT License
Classifier: Development Status :: 2 - Pre-Alpha
Classifier: Programming Language :: Python
Classifier: Programming Language :: Python :: 3
Classifier: Intended Audience :: Science/Research
License-File: LICENSE
Requires-Dist: psutil
Requires-Dist: pandas
